{
  "id": "laravel-middleware",
  "category": "backend",
  "name": "laravel",
  "spec_type": "middleware",
  "title": "Middleware",
  "description": "Laravel middleware for request filtering",
  "content": "<?php\n\nnamespace App\\Http\\Middleware;\n\nuse Closure;\nuse Illuminate\\Http\\Request;\nuse Symfony\\Component\\HttpFoundation\\Response;\n\nclass {MiddlewareName}\n{\n    public function handle(Request $request, Closure $next): Response\n    {\n        // Pre-request logic\n        if (! $this->shouldAllow($request)) {\n            abort(403, 'Unauthorized action.');\n        }\n\n        $response = $next($request);\n\n        // Post-request logic\n        return $response;\n    }\n\n    private function shouldAllow(Request $request): bool\n    {\n        // Implement your logic\n        return true;\n    }\n}",
  "language": "php",
  "framework_version": null,
  "ignore_patterns": [
    "vendor/*"
  ],
  "file_extensions": [
    "php"
  ],
  "is_active": true,
  "metadata": {
    "created_at": "2025-12-29T09:58:45.175656Z",
    "updated_at": "2025-12-29T09:58:45.175656Z"
  }
}